screen_search/__init__.py
screen_search/screen_search.py
screen_search-1.0.dist-info/LICENSE.txt
screen_search-1.0.dist-info/METADATA
screen_search-1.0.dist-info/WHEEL
screen_search-1.0.dist-info/top_level.txt
screen_search-1.0.dist-info/RECORD
