Metadata-Version: 2.1
Name: screen-search
Version: 1.0
Summary: A small python library use to  Searchs for an image on the screen
Home-page: https://notabug.org/alimiracle/screen_search
Author: alimiracle
Author-email: alimiracle@riseup.net
License: UNKNOWN
Platform: UNKNOWN
Classifier: Programming Language :: Python
Classifier: License :: OSI Approved :: GNU Affero General Public License v3
Classifier: Operating System :: OS Independent
Requires-Dist: opencv-python
Requires-Dist: pyautogui
Requires-Dist: numpy
Requires-Dist: pyobjc-core ; platform_system == "Darwin"
Requires-Dist: pyobjc ; platform_system == "Darwin"
Requires-Dist: Xlib ; platform_system == "Linux" and python_version < "3.0"
Requires-Dist: python3-Xlib ; platform_system == "Linux" and python_version >= "3.0"
